rqeuets/__init__.py
rqeuets-0.0.3.dist-info/METADATA
rqeuets-0.0.3.dist-info/WHEEL
rqeuets-0.0.3.dist-info/top_level.txt
rqeuets-0.0.3.dist-info/RECORD
